prody2/__init__.py
prody2/bibtex.py
prody2/constants.py
prody2/icon.png
prody2/protocols.conf
prody2/objects/__init__.py
prody2/objects/data.py
prody2/protocols/__init__.py
prody2/protocols/protocol_anm.py
prody2/protocols/protocol_atoms.py
prody2/protocols/protocol_clustenm.py
prody2/protocols/protocol_compare.py
prody2/protocols/protocol_defvec.py
prody2/protocols/protocol_domdec.py
prody2/protocols/protocol_edit.py
prody2/protocols/protocol_ensemble.py
prody2/protocols/protocol_gnm.py
prody2/protocols/protocol_import.py
prody2/protocols/protocol_modes_base.py
prody2/protocols/protocol_pca.py
prody2/protocols/protocol_pdbfixer.py
prody2/protocols/protocol_project.py
prody2/protocols/protocol_rmsd.py
prody2/protocols/protocol_rtb.py
prody2/tests/__init__.py
prody2/tests/test_clustenm.py
prody2/tests/test_core.py
prody2/tests/test_gnm.py
prody2/tests/test_pca.py
prody2/viewers/__init__.py
prody2/viewers/viewer_compare.py
prody2/viewers/viewer_domdec.py
prody2/viewers/viewer_gnm.py
prody2/viewers/viewer_modes.py
prody2/viewers/viewer_project.py
prody2/wizards/__init__.py
prody2/wizards/wizard_order_chains.py
scipion_em_prody-3.3.0.dist-info/LICENSE
scipion_em_prody-3.3.0.dist-info/METADATA
scipion_em_prody-3.3.0.dist-info/WHEEL
scipion_em_prody-3.3.0.dist-info/entry_points.txt
scipion_em_prody-3.3.0.dist-info/top_level.txt
scipion_em_prody-3.3.0.dist-info/RECORD
