Metadata-Version: 2.1
Name: scipion-em-prody
Version: 3.3.0
Summary: Scipion plugin for ProDy, the Bahar lab Python Package for Protein Dynamics Analysis
Home-page: https://github.com/scipion-em/scipion-em-prody
Author: James Krieger
Author-email: jmkrieger@cnb.csic.es
License: UNKNOWN
Keywords: scipion cryoem imageprocessing scipion-3.0 prody-2.0
Platform: UNKNOWN
Requires-Dist: threadpoolctl ==3.1.0
